ai_cli/__init__.py
ai_cli/bot/__init__.py
ai_cli/bot/bard.py
ai_cli/bot/bing.py
ai_cli/bot/gemini.py
ai_cli/bot/token.py
ai_cli/cli.py
ai_cli/git.py
ai_cli/setting.py
py_ai_cli-0.5.4.dist-info/entry_points.txt
py_ai_cli-0.5.4.dist-info/WHEEL
py_ai_cli-0.5.4.dist-info/METADATA
py_ai_cli-0.5.4.dist-info/licenses/LICENSE
py_ai_cli-0.5.4.dist-info/RECORD
