Metadata-Version: 2.1
Name: py_ai_cli
Version: 0.5.4
Summary: This CLI tool allows you to easily chat with chatGPT in the command line. You can chat with it, ask questions, and even translate text. It also
License: MIT
Author-email: Yufei Kang <kou.uhi.x@gmail.com>
Requires-Python: >=3.9
Requires-Dist: BardApi>=0.1.38
Requires-Dist: EdgeGPT>=0.1.22.1
Requires-Dist: google-generativeai>=0.3.2
Requires-Dist: openai>=1.10.0
Requires-Dist: pyperclip>=1.8.2
Requires-Dist: pysocks>=1.7.1
Requires-Dist: rich>=13.3.1
Requires-Dist: tiktoken>=0.7.0
Project-URL: Documentation, https://github.com/yufeikang/ai-cli/blob/main/README.md
Project-URL: Repository, https://github.com/yufeikang/ai-cli
